nacos_mcp_wrapper/__init__.py
nacos_mcp_wrapper/server/__init__.py
nacos_mcp_wrapper/server/nacos_mcp.py
nacos_mcp_wrapper/server/nacos_server.py
nacos_mcp_wrapper/server/nacos_settings.py
nacos_mcp_wrapper/server/utils.py
nacos_mcp_wrapper_python-1.1.0.dist-info/licenses/LICENSE
nacos_mcp_wrapper_python-1.1.0.dist-info/METADATA
nacos_mcp_wrapper_python-1.1.0.dist-info/WHEEL
nacos_mcp_wrapper_python-1.1.0.dist-info/top_level.txt
nacos_mcp_wrapper_python-1.1.0.dist-info/RECORD
