Metadata-Version: 2.4
Name: nacos-mcp-wrapper-python
Version: 1.1.0
Summary: Python sdk support mcp server auto register to nacos
Home-page: https://github.com/nacos-group/nacos-mcp-wrapper-python
Author: nacos
License: Apache License 2.0
Classifier: Topic :: Software Development :: Libraries :: Python Modules
Classifier: Operating System :: OS Independent
Classifier: Programming Language :: Python
Classifier: Programming Language :: Python :: 3.10
Requires-Python: >=3.10
License-File: LICENSE
Requires-Dist: psutil==7.0.0
Requires-Dist: anyio==4.9.0
Requires-Dist: mcp<2.0.0,>=1.25.0
Requires-Dist: nacos-sdk-python>=3.0.2
Requires-Dist: pydantic==2.11.3
Requires-Dist: pydantic-settings==2.9.1
Requires-Dist: jsonref==1.1.0
Requires-Dist: uvicorn==0.34.2
Dynamic: author
Dynamic: classifier
Dynamic: description
Dynamic: description-content-type
Dynamic: home-page
Dynamic: license
Dynamic: license-file
Dynamic: requires-dist
Dynamic: requires-python
Dynamic: summary
